swpclib/__init__.py
swpclib/alerts.py
swpclib/animate.py
swpclib/cli.py
swpclib/swpclib.py
swpclib-4.3.7.dist-info/LICENSE
swpclib-4.3.7.dist-info/METADATA
swpclib-4.3.7.dist-info/WHEEL
swpclib-4.3.7.dist-info/entry_points.txt
swpclib-4.3.7.dist-info/top_level.txt
swpclib-4.3.7.dist-info/RECORD
