Metadata-Version: 2.1
Name: swpclib
Version: 4.3.7
License-File: LICENSE
Requires-Dist: aiohttp >=3.8
Requires-Dist: pillow >=10.1
Requires-Dist: click >=8.1.7
